{
   "description": "This file is generated by qmake to be read by androiddeployqt and should not be modified by hand.",
   "qt": "V:/Qt/5.15.2/android",
   "sdk": "C:\\Users\\webma\\AppData\\Local\\Android\\Sdk",
   "sdkBuildToolsRevision": "34.0.0",
   "ndk": "C:\\Users\\webma\\AppData\\Local\\Android\\Sdk\\ndk\\21.3.6528147",
   "toolchain-prefix": "llvm",
   "tool-prefix": "llvm",
   "ndk-host": "windows-x86_64",
   "architectures": {"arm64-v8a":"aarch64-linux-android"},
   "android-package-source-directory": "V:/Vulkan/VulkanCapsViewerMaster/android",
   "android-min-sdk-version": "21",
   "android-target-sdk-version": "28",
   "qml-root-path": "V:/Vulkan/VulkanCapsViewerMaster",
   "stdcpp-path": "C:\\Users\\webma\\AppData\\Local\\Android\\Sdk\\ndk\\21.3.6528147/toolchains/llvm/prebuilt/windows-x86_64/sysroot/usr/lib/",
   "qrcFiles": "V:/Vulkan/VulkanCapsViewerMaster/vulkancapsviewer.qrc",
   "application-binary": "vulkanCapsViewer"
}
